Workbook

Sheet Guidance
B8: Implementation Guidance This Excel sheet must be removed from the final version of the document.
B10: Design This spreadsheet has been designed using CertiKit's colour scheme. To choose a different colour scheme, go to the Page Layout ribbon, select Themes and choose a different style.
B12: Purpose of this document This document sets out which of the controls from the standard have been included or excluded and their implementation status.
B14: Areas of the standard addressed This document addresses the following sections of the ISO/IEC 27001 standard: 6 Planning 6.1 Actions to address risks and opportunities 6.1.3 Information security risk treatment - item d)
B16: General guidance This document, as well as being required by the ISO/IEC 27001 standard, is a very useful summary of how you have implemented your ISMS and will be handy during the certification audit. In general you should implement all of the controls set out in the standard unless there are very clear reasons why not. In the main such reasons will usually be that the area of business or technology addressed does not exist in your organisation, but there may not be many of these. A number of charts have been provided and it is up to you to decide which form of presentation you find most helpful.
B18: Review frequency The Statement of Applicability should be reviewed in conjunction with your risk assessment, at least once a year.
B20: Toolkit version number ISO/IEC 27001 Toolkit Version 12
B22: Copyright notice Except for any specifically identified third-party works included, this document has been authored by CertiKit, and is ©CertiKit except as stated below. CertiKit is a company registered in England and Wales with company number 6432088.
B24: Licence terms This document is licensed on and subject to the standard licence terms of CertiKit, available on request, or by download from our website. All other rights are reserved. Unless you have purchased this product you only have an evaluation licence. If this product was purchased, a full licence is granted to the person identified as the licensee in the relevant purchase order. The standard licence terms include special terms relating to any third party copyright included in this document.
B26: Disclaimer Please Note: Your use of and reliance on this document template is at your sole risk. Document templates are intended to be used as a starting point only from which you will create your own document and to which you will apply all reasonable quality checks before use. Therefore please note that it is your responsibility to ensure that the content of any document you create that is based on our templates is correct and appropriate for your needs and complies with relevant laws in your country. You should take all reasonable and proper legal and other professional advice before using this document. CertiKit makes no claims, promises, or guarantees about the accuracy, completeness, or adequacy of our document templates, assumes no duty of care to any person with respect its document templates or their contents, and expressly excludes and disclaims liability for any cost, expense, loss or damage suffered or incurred in reliance on our document templates, or in expectation of our document templates meeting your needs, including (without limitation) as a result of misstatements, errors and omissions in their contents.

Sheet Version
B8: Version information
B10: Security classification
B11: Version
B12: Dated
B13: Approval

Sheet ISO27001 Annex A Applicability
F7: Terms used
B8: Information security management systems: Requirements | F8: ISMS: Information Security Management System
B9: Note: Only those controls that are listed in Annex A of the ISO/IEC 27001 standard are shown here.
B12: AREA/SECTION | C12: CONTROL | D12: CONTROL APPLICABLE? | E12: CONTROL IMPLEMENTED? | F12: JUSTIFICATION FOR INCLUSION OR EXCLUSION | G12: COMMENTS
B14: A.5 Organizational controls
C15: A.5.1 Policies for information security | D15: Yes | E15: Yes
C16: A.5.2 Information security roles and responsibilities | D16: Yes | E16: Yes
C17: A.5.3 Segregation of duties | D17: Yes | E17: Yes
C18: A.5.4 Management responsibilities | D18: Yes | E18: Yes
C19: A.5.5 Contact with authorities | D19: Yes | E19: Yes
C20: A.5.6 Contact with special interest groups | D20: Yes | E20: Yes
C21: A.5.7 Threat intelligence | D21: Yes | E21: Yes
C22: A.5.8 Information security in project management | D22: Yes | E22: Yes
C23: A.5.9 Inventory of information and other associated assets | D23: Yes | E23: Yes
C24: A.5.10 Acceptable use of information and other associated assets | D24: Yes | E24: Yes
C25: A.5.11 Return of assets | D25: Yes | E25: Yes
C26: A.5.12 Classification of information | D26: Yes | E26: Yes
... C51: A.5.37 Documented operating procedures | D51: Yes | E51: Yes
C53: Totals: | D53: =+COUNTIF(D15:D51,"Yes") -> 37 | E53: =+COUNTIF(E15:E51,"Yes") -> 37
B55: A.6 People controls
C56: A.6.1 Screening | D56: Yes | E56: Yes
C57: A.6.2 Terms and conditions of employment | D57: Yes | E57: Yes
C58: A.6.3 Information security awareness, education and training | D58: Yes | E58: Yes
C59: A.6.4 Disciplinary process | D59: Yes | E59: Yes
C60: A.6.5 Responsibilities after termination or change of employment | D60: Yes | E60: Yes
C61: A.6.6 Confidentiality or non-disclosure agreements | D61: Yes | E61: Yes
C62: A.6.7 Remote working | D62: Yes | E62: Yes
C63: A.6.8 Information security event reporting | D63: Yes | E63: Yes
C65: Totals: | D65: =+COUNTIF(D56:D63,"Yes") -> 8 | E65: =+COUNTIF(E56:E63,"Yes") -> 8
B67: A.7 Physical controls
C68: A.7.1 Physical security perimeters | D68: Yes | E68: Yes
C69: A.7.2 Physical entry | D69: Yes | E69: Yes
C70: A.7.3 Securing offices, rooms and facilities | D70: Yes | E70: Yes
C71: A.7.4 Physical security monitoring | D71: Yes | E71: Yes
C72: A.7.5 Protecting against physical and environmental threats | D72: Yes | E72: Yes
C73: A.7.6 Working in secure areas | D73: Yes | E73: Yes
C74: A.7.7 Clear desk and clear screen | D74: Yes | E74: Yes
C75: A.7.8 Equipment siting and protection | D75: Yes | E75: Yes
C76: A.7.9 Security of assets off-premises | D76: Yes | E76: Yes
C77: A.7.10 Storage media | D77: Yes | E77: Yes
C78: A.7.11 Supporting utilities | D78: Yes | E78: Yes
C79: A.7.12 Cabling security | D79: Yes | E79: Yes
... C81: A.7.14 Secure disposal or re-use of equipment | D81: Yes | E81: Yes
C83: Totals: | D83: =+COUNTIF(D68:D81,"Yes") -> 14 | E83: =+COUNTIF(E68:E81,"Yes") -> 14
B85: A.8 Technological controls
C86: A.8.1 User endpoint devices | D86: Yes | E86: Yes
C87: A.8.2 Privileged access rights | D87: Yes | E87: Yes
C88: A.8.3 Information access restriction | D88: Yes | E88: Yes
C89: A.8.4 Access to source code | D89: Yes | E89: Yes
C90: A.8.5 Secure authentication | D90: Yes | E90: Yes
C91: A.8.6 Capacity management | D91: Yes | E91: Yes
C92: A.8.7 Protection against malware | D92: Yes | E92: Yes
C93: A.8.8 Management of technical vulnerabilities | D93: Yes | E93: Yes
C94: A.8.9 Configuration management | D94: Yes | E94: Yes
C95: A.8.10 Information deletion | D95: Yes | E95: Yes
C96: A.8.11 Data masking | D96: Yes | E96: Yes
C97: A.8.12 Data leakage prevention | D97: Yes | E97: Yes
... C119: A.8.34 Protection of information systems during audit testing | D119: Yes | E119: Yes
C121: Totals: | D121: =+COUNTIF(D86:D119,"Yes") -> 34 | E121: =+COUNTIF(E86:E119,"Yes") -> 34

Sheet ISO27001 Annex A Dashboard
B8: ISO/IEC 27001 Statement of Applicability dashboard
B9: To refresh chart data, click on “Refresh All” on the Data ribbon.
B11: Statement of applicability results
B13: AREA OF STANDARD | C13: NO OF CONTROLS | D13: APPLICABLE CONTROLS | E13: % CONTROLS APPLICABLE | F13: CONTROLS IMPLEMENTED | G13: % APP CONTROLS IMPLEMENTED | I13: ISO/IEC 27001 Annex A controls percentage of controls applicable and implemented radar chart
B14: A.5 Organizational controls | C14: 37 | D14: ='ISO27001 Annex A Applicability'!D53 -> 37 | E14: =ISO27001ApplicabilityTableResults11[[#This Row],[APPLICABLE CONTROLS]]/ISO27001ApplicabilityTableResults11[[#This Row],[NO OF CONTROLS]] -> 1 | F14: ='ISO27001 Annex A Applicability'!E53 -> 37 | G14: =IF(D14=0,1,+F14/D14) -> 1
B15: A.6 People controls | C15: 8 | D15: ='ISO27001 Annex A Applicability'!D65 -> 8 | E15: =ISO27001ApplicabilityTableResults11[[#This Row],[APPLICABLE CONTROLS]]/ISO27001ApplicabilityTableResults11[[#This Row],[NO OF CONTROLS]] -> 1 | F15: ='ISO27001 Annex A Applicability'!E65 -> 8 | G15: =IF(D15=0,1,+F15/D15) -> 1
B16: A.7 Physical controls | C16: 14 | D16: ='ISO27001 Annex A Applicability'!D83 -> 14 | E16: =ISO27001ApplicabilityTableResults11[[#This Row],[APPLICABLE CONTROLS]]/ISO27001ApplicabilityTableResults11[[#This Row],[NO OF CONTROLS]] -> 1 | F16: ='ISO27001 Annex A Applicability'!E83 -> 14 | G16: =IF(D16=0,1,+F16/D16) -> 1
B17: A.8 Technological controls | C17: 34 | D17: ='ISO27001 Annex A Applicability'!D121 -> 34 | E17: =ISO27001ApplicabilityTableResults11[[#This Row],[APPLICABLE CONTROLS]]/ISO27001ApplicabilityTableResults11[[#This Row],[NO OF CONTROLS]] -> 1 | F17: ='ISO27001 Annex A Applicability'!E121 -> 34 | G17: =IF(D17=0,1,+F17/D17) -> 1
B18: Total | C18: =SUBTOTAL(109,ISO27001ApplicabilityTableResults11[NO OF CONTROLS]) -> 93 | D18: =SUBTOTAL(109,ISO27001ApplicabilityTableResults11[APPLICABLE CONTROLS]) -> 93 | E18: =SUBTOTAL(101,ISO27001ApplicabilityTableResults11[% CONTROLS APPLICABLE]) -> 1 | F18: =SUBTOTAL(109,ISO27001ApplicabilityTableResults11[CONTROLS IMPLEMENTED]) -> 93 | G18: =SUBTOTAL(101,ISO27001ApplicabilityTableResults11[% APP CONTROLS IMPLEMENTED]) -> 1
B22: ISO/IEC 27001 Annex A controls number of controls applicable and implemented
I38: ISO/IEC 27001 Annex A controls percentage of controls applicable and implemented

Sheet ISO27001 Applicability Table
B4: ISO/IEC 27001 Statement of Applicability results
B6: AREA OF STANDARD | C6: NO OF CONTROLS | D6: APPLICABLE CONTROLS | E6: % CONTROLS APPLICABLE | F6: CONTROLS IMPLEMENTED | G6: % APP CONTROLS IMPLEMENTED
B7: A.5 Organizational controls | C7: 37 | D7: ='ISO27001 Annex A Applicability'!D53 -> 37 | E7: =ISO27001ApplicabilityTableResults[[#This Row],[APPLICABLE CONTROLS]]/ISO27001ApplicabilityTableResults[[#This Row],[NO OF CONTROLS]] -> 1 | F7: ='ISO27001 Annex A Applicability'!E53 -> 37 | G7: =IF(D7=0,1,+F7/D7) -> 1
B8: A.6 People controls | C8: 8 | D8: ='ISO27001 Annex A Applicability'!D65 -> 8 | E8: =ISO27001ApplicabilityTableResults[[#This Row],[APPLICABLE CONTROLS]]/ISO27001ApplicabilityTableResults[[#This Row],[NO OF CONTROLS]] -> 1 | F8: ='ISO27001 Annex A Applicability'!E65 -> 8 | G8: =IF(D8=0,1,+F8/D8) -> 1
B9: A.7 Physical controls | C9: 14 | D9: ='ISO27001 Annex A Applicability'!D83 -> 14 | E9: =ISO27001ApplicabilityTableResults[[#This Row],[APPLICABLE CONTROLS]]/ISO27001ApplicabilityTableResults[[#This Row],[NO OF CONTROLS]] -> 1 | F9: ='ISO27001 Annex A Applicability'!E83 -> 14 | G9: =IF(D9=0,1,+F9/D9) -> 1
B10: A.8 Technological controls | C10: 34 | D10: ='ISO27001 Annex A Applicability'!D121 -> 34 | E10: =ISO27001ApplicabilityTableResults[[#This Row],[APPLICABLE CONTROLS]]/ISO27001ApplicabilityTableResults[[#This Row],[NO OF CONTROLS]] -> 1 | F10: ='ISO27001 Annex A Applicability'!E121 -> 34 | G10: =IF(D10=0,1,+F10/D10) -> 1
B11: Total | C11: =SUBTOTAL(109,ISO27001ApplicabilityTableResults[NO OF CONTROLS]) -> 93 | D11: =SUBTOTAL(109,ISO27001ApplicabilityTableResults[APPLICABLE CONTROLS]) -> 93 | E11: =SUBTOTAL(101,ISO27001ApplicabilityTableResults[% CONTROLS APPLICABLE]) -> 1 | F11: =SUBTOTAL(109,ISO27001ApplicabilityTableResults[CONTROLS IMPLEMENTED]) -> 93 | G11: =SUBTOTAL(101,ISO27001ApplicabilityTableResults[% APP CONTROLS IMPLEMENTED]) -> 1

Sheet ISO27001 Results Chart
B4: ISO/IEC 27001 Annex A Controls Number of Controls Applicable and Implemented
B6: AREA OF STANDARD | C6: APPLICABLE CONTROLS | D6: CONTROLS IMPLEMENTED
B7: A.8 Technological controls | C7: 34 | D7: 34
B8: A.7 Physical controls | C8: 14 | D8: 14
B9: A.6 People controls | C9: 8 | D9: 8
B10: A.5 Organizational controls | C10: 37 | D10: 37

Sheet ISO27001 % Results Chart
B4: ISO/IEC 27001 Annex A Controls Percentage of Controls Applicable and Implemented
B6: AREA OF STANDARD | C6: % APP CONTROLS IMPLEMENTED | D6: % CONTROLS APPLICABLE
B7: A.5 Organizational controls | C7: 1 | D7: 1
B8: A.6 People controls | C8: 1 | D8: 1
B9: A.7 Physical controls | C9: 1 | D9: 1
B10: A.8 Technological controls | C10: 1 | D10: 1

Sheet ISO27001 % Radar Chart
B4: ISO/IEC 27001 Annex A Controls Percentage of Controls Applicable and Implemented Radar Chart
B6: AREA OF STANDARD | C6: % APP CONTROLS IMPLEMENTED | D6: % CONTROLS APPLICABLE
B7: A.5 Organizational controls | C7: 1 | D7: 1
B8: A.6 People controls | C8: 1 | D8: 1
B9: A.7 Physical controls | C9: 1 | D9: 1
B10: A.8 Technological controls | C10: 1 | D10: 1
